distributions/Binomialdistribution.py
distributions/Gaussiandistribution.py
distributions/Generaldistribution.py
distributions/__init__.py
zzhprobsecond-0.3.dist-info/METADATA
zzhprobsecond-0.3.dist-info/WHEEL
zzhprobsecond-0.3.dist-info/top_level.txt
zzhprobsecond-0.3.dist-info/RECORD
